setup.py
alex_message_client.egg-info/PKG-INFO
alex_message_client.egg-info/SOURCES.txt
alex_message_client.egg-info/dependency_links.txt
alex_message_client.egg-info/requires.txt
alex_message_client.egg-info/top_level.txt
client/__init__.py
client/client.py
client/client/__init__.py
client/client/client_gui.py
client/client/client_window.py
client/client/database.py
client/client/transport.py
client/common/__init__.py
client/common/decos.py
client/common/descryptors.py
client/common/errors.py
client/common/metaclasses.py
client/common/utils.py
client/common/variables.py
client/logs/__init__.py
client/logs/config_client_log.py
client/logs/config_server_log.py
client/unit_tests/__init__.py