Metadata-Version: 1.0
Name: alex-message-client
Version: 0.8.0
Summary: alex_message_client
Home-page: UNKNOWN
Author: Alexey V. Danilyuk
Author-email: danilyuk-aleksey@mail.ru
License: UNKNOWN
Platform: UNKNOWN
